pyimportr/__init__.py
pyimportr/pyimport.py
pyimportR-0.9.0.dist-info/METADATA
pyimportR-0.9.0.dist-info/WHEEL
pyimportR-0.9.0.dist-info/top_level.txt
pyimportR-0.9.0.dist-info/RECORD
