Metadata-Version: 2.1
Name: pyimportR
Version: 0.9.0
Summary: Pandas Code Importer with GUI Interface simplifies the process of adding Pandas code into Python scripts. Through a user-friendly GUI, users can easily select and insert Pandas functions, automating repetitive tasks and enhancing productivity in data analysis projects.
Author: Manoj Khandelwal
Author-email: tr.manojkhandelwal@gmail.com
Keywords: python,pandas,gui,importer,pandas importer,import,pyimport,pyimport-0.9.0
Classifier: Development Status :: 1 - Planning
Classifier: Intended Audience :: Developers
Classifier: Programming Language :: Python
Classifier: Operating System :: Unix
Classifier: Operating System :: MacOS :: MacOS X
Classifier: Operating System :: Microsoft :: Windows
Requires-Dist: pandas
Requires-Dist: openpyxl
Requires-Dist: pillow
